MANIFEST.in
README.md
setup.py
dgx/__init__.py
dgx/__main__.py
dgx/_version.py
dgx/dgx.py
dgx.egg-info/PKG-INFO
dgx.egg-info/SOURCES.txt
dgx.egg-info/dependency_links.txt
dgx.egg-info/entry_points.txt
dgx.egg-info/requires.txt
dgx.egg-info/top_level.txt
dgx/default/default_controller.py
dgx/default/docs/search.yml
dgx/optional/brand/brand_controller.py
dgx/optional/brand/docs/get_all.yml
dgx/optional/brand/docs/get_by_dealer.yml
dgx/optional/brand/docs/search.yml
dgx/optional/personnel/personnel_controller.py
dgx/optional/personnel/docs/get_by_id.yml
dgx/optional/personnel/docs/get_roles.yml
dgx/optional/personnel/docs/search.yml
dgx/optional/personnel/docs/update.yml
dgx/resources/.gitignore
dgx/resources/.gitlab-ci.yml
dgx/resources/__init__.py
dgx/resources/app.py
dgx/resources/const.py
dgx/resources/dgapi.py
dgx/resources/gitlab_integration.py
dgx/resources/mongoCon.py
dgx/resources/requirements.txt
dgx/resources/runServer.py
dgx/resources/telegramapi.py
dgx/resources/modules/authentication/authentication.py
dgx/resources/modules/authentication/docs/is_authorized.yml
dgx/resources/modules/authentication/docs/logout.yml
dgx/resources/modules/authentication/docs/one_authentication.yml
dgx/resources/modules/item/item_controller.py
dgx/resources/modules/item/docs/add.yml
dgx/resources/modules/item/docs/delete_by_id.yml
dgx/resources/modules/item/docs/get_all_items.yml
dgx/resources/modules/recycle/recycle_controller.py
dgx/resources/modules/recycle/docs/delete_all.yml
dgx/resources/modules/recycle/docs/delete_by_id.yml
dgx/resources/modules/recycle/docs/get_by_id.yml
dgx/resources/modules/recycle/docs/recover_all.yml
dgx/resources/modules/recycle/docs/recover_by_id.yml
dgx/resources/modules/recycle/docs/search.post.yml
dgx/resources/modules/recycle/docs/search.yml
dgx/resources/utils/decorators.py
dgx/resources/utils/helpers.py
dgx/resources/utils/recycle.py
dgx/resources/utils/responses.py