Metadata-Version: 2.1
Name: dgx
Version: 0.0.24
Summary: Dealergeek API
Home-page: https://github.com/jaguilar08/dgx
Author: Jeff Aguilar
Author-email: jeff.aguilar.06@gmail.com
License: MIT
Download-URL: https://github.com/jaguilar08/dgx/archive/refs/tags/0.1.tar.gz
Keywords: DEALERGEEK,API
Platform: UNKNOWN
Classifier: Development Status :: 3 - Alpha
Classifier: Intended Audience :: Developers
Classifier: Topic :: Software Development :: Build Tools
Classifier: License :: OSI Approved :: MIT License
Classifier: Programming Language :: Python :: 3.6
Classifier: Programming Language :: Python :: 3.7
Classifier: Programming Language :: Python :: 3.8
Classifier: Programming Language :: Python :: 3.9
